esipysi/__init__.py
esipysi/auth.py
esipysi/esipysi.py
esipysi/esiresponse.py
esipysi/op.py
esipysi/cache/__init__.py
esipysi/cache/cache.py
esipysi/cache/mock.py
esipysi/cache/redis.py
EsiPysi-0.9.0.dist-info/LICENSE
EsiPysi-0.9.0.dist-info/METADATA
EsiPysi-0.9.0.dist-info/WHEEL
EsiPysi-0.9.0.dist-info/license.txt
EsiPysi-0.9.0.dist-info/top_level.txt
EsiPysi-0.9.0.dist-info/RECORD
