Metadata-Version: 2.1
Name: EsiPysi
Version: 0.9.0
Summary: A client for ESI, the API for Eve Online
Home-page: https://github.com/FlyingKiwiBird/EsiPysi
Author: Flying Kiwi
Author-email: github@flyingkiwibird.com
License: MIT
Keywords: Esi Eve Python Api
Platform: UNKNOWN
Classifier: Development Status :: 3 - Alpha
Classifier: Intended Audience :: Developers
Classifier: Topic :: Utilities
Classifier: Programming Language :: Python
Classifier: Programming Language :: Python :: 3.3
Classifier: Programming Language :: Python :: 3.4
Classifier: Programming Language :: Python :: 3.5
Classifier: Programming Language :: Python :: 3.6
Requires-Dist: aiohttp
Requires-Dist: aiodns
Requires-Dist: requests
Requires-Dist: redis
